pychan/__init__.py
pychan/fourchan.py
pychan/fuuka.py
py_chan_api-0.1.3.dist-info/LICENSE
py_chan_api-0.1.3.dist-info/METADATA
py_chan_api-0.1.3.dist-info/WHEEL
py_chan_api-0.1.3.dist-info/top_level.txt
py_chan_api-0.1.3.dist-info/RECORD
