Metadata-Version: 2.1
Name: py-chan-api
Version: 0.1.3
Summary: A Python wrapper for the 4chan API and other imageboards
Home-page: https://github.com/shiimizu/py-chan-api
Author: Shiimizu
Author-email: shiimizu@protonmail.com
License: MIT
Project-URL: Bug Reports, https://github.com/shiimizu/py-chan-api/issues
Project-URL: Source, https://github.com/shiimizu/py-chan-api
Keywords: 4chan api imageboard wrapper
Platform: UNKNOWN
Classifier: Development Status :: 3 - Alpha
Classifier: Intended Audience :: Developers
Classifier: License :: OSI Approved :: MIT License
Classifier: Topic :: Software Development :: Code Generators
Classifier: Topic :: Software Development :: Libraries
Classifier: Topic :: Software Development :: Libraries :: Python Modules
Classifier: Operating System :: Microsoft :: Windows
Classifier: Operating System :: POSIX
Classifier: Operating System :: Unix
Classifier: Operating System :: MacOS
Classifier: Natural Language :: English
Requires-Python: >=3.0, <4
